README.md
setup.py
mukesh_api/__init__.py
mukesh_api/passgen.py
mukesh_api.egg-info/PKG-INFO
mukesh_api.egg-info/SOURCES.txt
mukesh_api.egg-info/dependency_links.txt
mukesh_api.egg-info/requires.txt
mukesh_api.egg-info/top_level.txt