Metadata-Version: 2.1
Name: mukesh-api
Version: 0.0.1
Summary: python api hub |telegram bots 
Author: Mukesh | noob-mukesh
Author-email: itzcodermukesh@gmail.com
Project-URL: Tracker, https://github.com/noob-mukesh/API-HUB/issues
Project-URL: Community, https://t.me/MR_SUKKUN
Project-URL: Source, https://github.com/noob-mukesh/API-HUB
Keywords: python api for telegram bot apihub  fastapi flask
Classifier: Development Status :: 5 - Production/Stable
Classifier: Intended Audience :: Developers
Classifier: Natural Language :: English
Classifier: Operating System :: OS Independent
Classifier: Programming Language :: Python
Classifier: Programming Language :: Python :: 3
Classifier: Programming Language :: Python :: 3.7
Classifier: Programming Language :: Python :: 3.8
Classifier: Programming Language :: Python :: 3.9
Classifier: Programming Language :: Python :: 3.10
Classifier: Programming Language :: Python :: 3.11
Classifier: Programming Language :: Python :: Implementation
Classifier: Programming Language :: Python :: Implementation :: CPython
Classifier: Programming Language :: Python :: Implementation :: PyPy
Classifier: Topic :: Internet
Classifier: Topic :: Communications
Classifier: Topic :: Communications :: Chat
Classifier: Topic :: Software Development :: Libraries
Classifier: Topic :: Software Development :: Libraries :: Python Modules
Classifier: Topic :: Software Development :: Libraries :: Application Frameworks
Requires-Python: ~=3.7
Requires-Dist: pytz>=2023.3
